LICENSE
MANIFEST.in
README.md
install.json
package.json
pyproject.toml
setup.py
tsconfig.json
inhpc_dm/__init__.py
inhpc_dm/_version.py
inhpc_dm/auth.py
inhpc_dm/browser_check.py
inhpc_dm/config.py
inhpc_dm/extension.py
inhpc_dm/fsmanager.py
inhpc_dm/handlers.py
inhpc_dm/metamanager.py
inhpc_dm/pathutils.py
inhpc_dm/tasks.py
inhpc_dm/uftp_handler.py
inhpc_dm.egg-info/PKG-INFO
inhpc_dm.egg-info/SOURCES.txt
inhpc_dm.egg-info/dependency_links.txt
inhpc_dm.egg-info/not-zip-safe
inhpc_dm.egg-info/requires.txt
inhpc_dm.egg-info/top_level.txt
inhpc_dm/contents_managers/__init__.py
inhpc_dm/contents_managers/absolute.py
inhpc_dm/labextension/package.json
inhpc_dm/labextension/schemas/inhpc_dm/package.json.orig
inhpc_dm/labextension/schemas/inhpc_dm/plugin.json
inhpc_dm/labextension/static/181.9195149b703808958532.js
inhpc_dm/labextension/static/213.d351208a942322a965e3.js
inhpc_dm/labextension/static/514.e429132dab57e5b43201.js
inhpc_dm/labextension/static/717.f778da20c8ab4bb4bbf8.js
inhpc_dm/labextension/static/956.5414436a736a2f1bc0f4.js
inhpc_dm/labextension/static/956.5414436a736a2f1bc0f4.js.LICENSE.txt
inhpc_dm/labextension/static/remoteEntry.6aad4a718f0ed88a2594.js
inhpc_dm/labextension/static/style.js
inhpc_dm/labextension/static/third-party-licenses.json
jupyter-config/server-config/inhpc_dm.json
src/auth.tsx
src/clipboard.ts
src/commands.ts
src/contents_proxy.ts
src/contents_utils.ts
src/dm_buttons.ts
src/dm_dialogs.ts
src/dm_filetree.ts
src/dm_handler.ts
src/dm_transferlist.ts
src/dm_widget.ts
src/drag.ts
src/filesystem.ts
src/icons.ts
src/index.tsx
src/progress.tsx
src/resources.tsx
src/settings.ts
src/svg.d.ts
src/tokens.ts
src/treefinder.ts
src/upload.ts
src/utils.ts
style/auth.css
style/index.css
style/index.js
style/treefinder.css
style/icons/drive.svg
style/icons/file-tree.svg
style/icons/jupyter-fs.svg
style/icons/left_arr.svg
style/icons/right_arr.svg
style/icons/visibility-off.svg
style/icons/visibility.svg